README.md
setup.py
johanna/__init__.py
johanna/private.py
johanna.egg-info/PKG-INFO
johanna.egg-info/SOURCES.txt
johanna.egg-info/dependency_links.txt
johanna.egg-info/not-zip-safe
johanna.egg-info/requires.txt
johanna.egg-info/top_level.txt