Metadata-Version: 1.1
Name: johanna
Version: 0.3.0
Summary: Sweet tiny app framework for Jenkins driven background apps
Home-page: https://github.com/turkishmaid/johanna
Author: Sara Ziner
Author-email: turkishmaid@example.com
License: MIT
Platform: UNKNOWN
Classifier: Development Status :: 3 - Alpha
Classifier: License :: OSI Approved :: MIT License
Classifier: Programming Language :: Python :: 3.7
Classifier: Programming Language :: Python :: 3.8
Classifier: Intended Audience :: Developers
Classifier: Topic :: Utilities
